gtcp/__init__.py
gtcp/client.py
gtcp/server.py
gtcp-0.3.7.dist-info/LICENSE
gtcp-0.3.7.dist-info/METADATA
gtcp-0.3.7.dist-info/WHEEL
gtcp-0.3.7.dist-info/top_level.txt
gtcp-0.3.7.dist-info/RECORD
