Metadata-Version: 2.1
Name: gtcp
Version: 0.3.7
Summary: Simple and secure TCP framework
Home-page: UNKNOWN
Author: Keizou Wang
Author-email: keizouw8@gmail.com
License: UNKNOWN
Keywords: python,tcp,crypto,sockets
Platform: UNKNOWN
Classifier: Development Status :: 3 - Alpha
Classifier: Intended Audience :: Developers
Classifier: Programming Language :: Python :: 2
Classifier: Programming Language :: Python :: 3
Classifier: Operating System :: OS Independent
Classifier: License :: OSI Approved :: Apache Software License
Requires-Dist: pycryptodome
